{"data": [{"datetime": 1755774000000, "symbol": "ARDRUSDT", "signal": "SELL", "entry": 0.08852, "stop_loss": null, "take_profit": null, "url": "https://www.tradingview.com/chart?symbol=ARDRUSDT"}, {"datetime": 1755774000000, "symbol": "BELUSDT", "signal": "SELL", "entry": 0.2537, "stop_loss": null, "take_profit": null, "url": "https://www.tradingview.com/chart?symbol=BELUSDT"}, {"datetime": 1755774000000, "symbol": "CTKUSDT", "signal": "SELL", "entry": 0.3167, "stop_loss": null, "take_profit": null, "url": "https://www.tradingview.com/chart?symbol=CTKUSDT"}, {"datetime": 1755774000000, "symbol": "FIOUSDT", "signal": "SELL", "entry": 0.01861, "stop_loss": null, "take_profit": null, "url": "https://www.tradingview.com/chart?symbol=FIOUSDT"}, {"datetime": 1755774000000, "symbol": "GMXUSDT", "signal": "SELL", "entry": 15.03, "stop_loss": null, "take_profit": null, "url": "https://www.tradingview.com/chart?symbol=GMXUSDT"}, {"datetime": 1755774000000, "symbol": "TOWNSUSDT", "signal": "SELL", "entry": 0.02648, "stop_loss": null, "take_profit": null, "url": "https://www.tradingview.com/chart?symbol=TOWNSUSDT"}]}