{
  "data": [
    { "datetime": 1755428400000, "symbol": "DYMUSDT", "signal": "BUY", "entry": 0.261, "stop_loss": null, "take_profit": null, "url": "https://www.tradingview.com/chart?symbol=DYMUSDT" },
    { "datetime": 1755428400000, "symbol": "RIFUSDT", "signal": "BUY", "entry": 0.0579, "stop_loss": null, "take_profit": null, "url": "https://www.tradingview.com/chart?symbol=RIFUSDT" },
    { "datetime": 1755428400000, "symbol": "XTZUSDT", "signal": "BUY", "entry": 0.8752, "stop_loss": null, "take_profit": null, "url": "https://www.tradingview.com/chart?symbol=XTZUSDT" }
  ]
}

